rr_batch/__init__.py
rr_batch/constants.py
rr_batch/sql.py
rr_batch/process/__init__.py
rr_batch/process/pressure.py
rr_batch/process/rating.py
rr_batch_process-1.4.dist-info/LICENSE
rr_batch_process-1.4.dist-info/METADATA
rr_batch_process-1.4.dist-info/WHEEL
rr_batch_process-1.4.dist-info/top_level.txt
rr_batch_process-1.4.dist-info/RECORD
