Metadata-Version: 2.1
Name: rr-batch-process
Version: 1.4
Summary: rr-batch-process
Home-page: https://upload.pypi.org/legacy/
Author: Yossi Arar
Author-email: yossiarar@gmail.com
License: MIT
Platform: UNKNOWN
Classifier: Programming Language :: Python :: 3
Classifier: License :: OSI Approved :: MIT License
Classifier: Operating System :: OS Independent
Requires-Python: >=3.9
License-File: LICENSE
Requires-Dist: rr-psychology
Requires-Dist: numpy
Requires-Dist: sklearn
